<annotation>
	<folder>590787567</folder>
	<filename>590787567_page-369.jpg</filename>
	<path>/Users/cengt/Documents/Code/shape_re/src/shape_re/pdf/590787567/page-369.jpg</path>
	<source>
		<database>Unknown</database>
	</source>
	<size>
		<width>595</width>
		<height>842</height>
		<depth>1</depth>
	</size>
	<segmented>0</segmented>
	<object>
		<name>circle</name>
		<pose>Unspecified</pose>
		<truncated>0</truncated>
		<difficult>0</difficult>
		<bndbox>
			<xmin>347</xmin>
			<ymin>154</ymin>
			<xmax>387</xmax>
			<ymax>335</ymax>
		</bndbox>
	</object>
	<object>
		<name>circle</name>
		<pose>Unspecified</pose>
		<truncated>0</truncated>
		<difficult>0</difficult>
		<bndbox>
			<xmin>402</xmin>
			<ymin>315</ymin>
			<xmax>440</xmax>
			<ymax>469</ymax>
		</bndbox>
	</object>
	<object>
		<name>circle</name>
		<pose>Unspecified</pose>
		<truncated>0</truncated>
		<difficult>0</difficult>
		<bndbox>
			<xmin>349</xmin>
			<ymin>365</ymin>
			<xmax>387</xmax>
			<ymax>511</ymax>
		</bndbox>
	</object>
	<object>
		<name>circle</name>
		<pose>Unspecified</pose>
		<truncated>0</truncated>
		<difficult>0</difficult>
		<bndbox>
			<xmin>403</xmin>
			<ymin>500</ymin>
			<xmax>442</xmax>
			<ymax>624</ymax>
		</bndbox>
	</object>
</annotation>
